unisi-0.4.6.dist-info/METADATA
unisi-0.4.6.dist-info/WHEEL
unisi-0.4.6.dist-info/entry_points.txt
unisi-0.4.6.dist-info/licenses/LICENSE
unisi/__init__.py
unisi/autotest.py
unisi/common.py
unisi/containers.py
unisi/dbunits.py
unisi/graphs.py
unisi/jsoncomparison/__init__.py
unisi/jsoncomparison/compare.py
unisi/jsoncomparison/config.py
unisi/jsoncomparison/errors.py
unisi/jsoncomparison/ignore.py
unisi/kdb.py
unisi/llmrag.py
unisi/multimon.py
unisi/proxy.py
unisi/reloader.py
unisi/server.py
unisi/tables.py
unisi/units.py
unisi/users.py
unisi/utils.py
unisi/voicecom.py
unisi/web/css/262.46daf72a.css
unisi/web/css/72.9393078c.css
unisi/web/css/app.36cc37f3.css
unisi/web/css/app.36cc37f3.css.gz
unisi/web/favicon.ico
unisi/web/fonts/KFOMCnqEu92Fr1ME7kSn66aGLdTylUAMQXC89YmC2DPNWuYjalmUiAw.2cafd699.woff
unisi/web/fonts/KFOMCnqEu92Fr1ME7kSn66aGLdTylUAMQXC89YmC2DPNWuZtalmUiAw.7f471697.woff
unisi/web/fonts/KFOMCnqEu92Fr1ME7kSn66aGLdTylUAMQXC89YmC2DPNWuaabVmUiAw.b69d1cce.woff
unisi/web/fonts/KFOMCnqEu92Fr1ME7kSn66aGLdTylUAMQXC89YmC2DPNWub2bVmUiAw.2115c3bd.woff
unisi/web/fonts/KFOMCnqEu92Fr1ME7kSn66aGLdTylUAMQXC89YmC2DPNWubEbFmUiAw.bb8ee9ee.woff
unisi/web/fonts/KFOMCnqEu92Fr1ME7kSn66aGLdTylUAMQXC89YmC2DPNWubEbVmUiAw.eb9d7304.woff
unisi/web/fonts/flUhRq6tzZclQEJ-Vdg-IuiaDsNa.4d73cb90.woff
unisi/web/fonts/flUhRq6tzZclQEJ-Vdg-IuiaDsNcIhQ8tQ.c5371cfb.woff2
unisi/web/icons/favicon-128x128.png
unisi/web/icons/favicon-16x16.png
unisi/web/icons/favicon-32x32.png
unisi/web/icons/favicon-96x96.png
unisi/web/index.html
unisi/web/js/262.977d8d88.js
unisi/web/js/262.977d8d88.js.gz
unisi/web/js/609.a5c4177e.js
unisi/web/js/72.a16d3634.js
unisi/web/js/917.e3f05280.js
unisi/web/js/935.a10cb1a0.js
unisi/web/js/app.90bb0b3b.js
unisi/web/js/echart.8f773fb7.js
unisi/web/js/echart.8f773fb7.js.gz
unisi/web/js/sigma.ce21336a.js
unisi/web/js/sigma.ce21336a.js.gz
unisi/web/js/vendor.6a64dcc5.js
unisi/web/js/vendor.6a64dcc5.js.gz
unisi-0.4.6.dist-info/RECORD
