Metadata-Version: 2.1
Name: unisi
Version: 0.4.6
Summary: Unified System Interface, GUI and Remote API
Author-Email: UNISI Tech <g.dernovoy@gmail.com>
License: Apache-2.0
Project-URL: Homepage, https://github.com/unisi-tech/unisi
Requires-Python: >=3.10
Requires-Dist: aiohttp
Requires-Dist: jsonpickle
Requires-Dist: pandas
Requires-Dist: requests
Requires-Dist: watchdog
Requires-Dist: websockets
Requires-Dist: websocket-client
Requires-Dist: cymple
Requires-Dist: kuzu
Requires-Dist: langchain
Requires-Dist: langchain-groq
Requires-Dist: langchain-community
Requires-Dist: langchain-openai
Requires-Dist: langchain-google-genai
Requires-Dist: langchain_mistralai
Requires-Dist: langchain-xai
Requires-Dist: word2number
